{"type":"PR","pr":{"number":194,"head":"02f8db791f95682cdc04604c06097f19be7e1bf5"},"user":"orkunkumkale","status":"draft","branch":"cms/2019-10-11-gerçeğin-sesi-2","collection":"series","title":"GERÇEĞİN SESİ 2","description":"Pastör Hakan Taştan'ın sunumu ve konuklarıyla birlikte Kutsal Kitap ışığında gerçekleştirdi \n\"Gerçeğin Sesi\" programını Kanal Hayat ekranlarından veya youtube sayfamızdan takip\n edebilirsiniz.\nEsen Kalın.","objects":{"entry":{"path":"content/series/2019-10-11-gerçeğin-sesi-2.md","sha":"0352bafdea32865ee66793e90a38f559994055f2"},"files":[]},"timeStamp":"2019-10-11T11:42:51.773Z"}