{"type":"PR","pr":{"number":556,"head":"b837f40ff254f755613e88458a69607054c28932"},"user":"orkunkumkale","status":"draft","branch":"cms/2019-10-10-kamil-musa","collection":"series","title":"Kamil Musa","description":"Kamil Musa'nın hazırlayıp sunduğu Kutsal Kitap temelindeki birbirinden farklı konuları Kanal Hayat ekranlarından veya youtube sayfamızdan takip edebilirsiniz.\nSevgiler.","objects":{"entry":{"path":"content/series/2019-10-10-kamil-musa.md","sha":"030314d5da33e35b387ffa219cacea88b3e68f70"},"files":[]},"timeStamp":"2019-11-03T11:47:56.416Z"}