{"type":"PR","pr":{"number":363,"head":"84972b1cfd4458c62474b2e15bf9819e4a05d130"},"user":"orkunkumkale","status":"pending_publish","branch":"cms/2019-10-07-hayattan-keyif-alın","collection":"series","title":"HAYATTAN KEYİF ALIN","description":"Zihnimizdeki kalıpları nasıl kırabiliriz? İnsan bağımlılıklarından nasıl özgür olur? Kitapları Çok Satan İncil Öğretmeni Joyce Meyer’den, hayatınızdan zevk almanız için teşvik dolu paylaşımlar. Joyce Meyer’i Kanal Hayat ekranlarından ve Youtube kanalımızdan takip edebilirsiniz.","objects":{"entry":{"path":"content/series/2019-10-07-hayattan-keyif-alın.md","sha":"4baf4e60852801a21796fc716cb6e596cc947398"},"files":[]},"timeStamp":"2019-10-26T08:00:11.875Z"}