{"type":"PR","pr":{"number":187,"head":"010c8eb79885617002d4a72214b5cc3a673e4fb8"},"user":"orkunkumkale","status":"draft","branch":"cms/2019-10-08-uyanış","collection":"series","title":"Uyanış","description":"Güçlü Erman'ın hazırlayıp sunduğu \"Uyanış\" adlı programını Kanal Hayat ekranlarından veya youtube sayfamızdan takip edebilirsiniz. Esen Kalın. ","objects":{"entry":{"path":"content/series/2019-10-08-uyanış.md","sha":"c12bf715d72d2bccc4753e632bb23455e27c248a"},"files":[]},"timeStamp":"2019-10-10T11:57:06.252Z"}