{"type":"PR","pr":{"number":280,"head":"3eaf598e483c98c972bb3ab0b5929d53be8731e3"},"user":"orkunkumkale","status":"draft","branch":"cms/2019-09-18-dar-kapidan-girenler-neden-hristiyan-oldum-8-sezon","collection":"series","title":"DAR KAPIDAN GİRENLER 8.SEZON","description":"Neden Hristiyan Oldum?\nAli Kalkandelen'in sunumu ve konuklarının katılımıyla gerçekleştirdiği \"Dar Kapıdan Girenler\" programını sayfamızdan takip edebilirsiniz.Esen Kalın.\nhttp://kanalhayat.tv/\nhttp://www.youtube.com/kanalhayatplay\nhttps://www.facebook.com/kanalhayat\nhttps://twitter.com/kanalhayat","objects":{"entry":{"path":"content/series/2019-09-18-dar-kapidan-girenler-neden-hristiyan-oldum-8-sezon.md","sha":"31da1dc05c72ab0f2a58421181262159f48ad764"},"files":[]},"timeStamp":"2019-10-25T12:32:38.954Z"}